arclia/stats/__init__.py
arclia/stats/_quantiles.py
arclia_stats-0.1.0.dist-info/METADATA
arclia_stats-0.1.0.dist-info/WHEEL
arclia_stats-0.1.0.dist-info/RECORD
