Metadata-Version: 2.1
Name: arclia-stats
Version: 0.1.0
Summary: Basic statistical functions
License: MIT
Author: Brian Lauber
Requires-Python: >=3.12,<4.0
Classifier: License :: OSI Approved :: MIT License
Classifier: Programming Language :: Python :: 3
Classifier: Programming Language :: Python :: 3.12
Requires-Dist: numpy (>=1.26.3,<2.0.0)
